{
  "brand": "Marantz",
  "products": [
    {
      "name": "CINEMA 30",
      "series": "CINEMA",
      "category": "AV receivari",
      "subcategory": "Nema",
      "description": "Vrhunski 11.4-kanalni AV receiver za kućno kino.",
      "longDescription": "Marantz CINEMA 30 je flagship 11.4-kanalni AV receiver s 11 kanala pojačanja, 13.4-kanalnom obradom, ESS Sabre DAC-ovima i Dirac Live Bass Control-om, pružajući izvanredan zvuk za kućne kino sustave i streaming.",
      "intended_use": ["Kućno kino", "Streaming"],
      "price_usd": 4500,
      "finishes": ["Crna", "Srebrno-zlatna"],
      "imageUrl": "https://raw.githubusercontent.com/MikiMix-Git/SonusArtBA/refs/heads/main/logos/Marantz.png",
      "warranty_duration": 2,
      "release_year": 2024,
      "comparison_score": 88,
      "specifications": {
        "type": "AV receiver",
        "min_frequency": 20,
        "max_frequency": 20000,
        "amplifier_power": "150W po kanalu (8Ω, 2 kanala)",
        "amplifier_power_watts": 150,
        "inputs": ["7x HDMI 2.1 (8K)", "2x optički", "2x koaksijalni", "4x analogni RCA", "Phono MM"],
        "outputs": ["2x HDMI (1x eARC)", "4x subwoofer", "13.4 pre-out"],
        "connectivity": ["HEOS", "Bluetooth", "AirPlay 2", "Wi-Fi", "Spotify Connect"],
        "dimensions": {
          "height_mm": 165,
          "width_mm": 440,
          "depth_mm": 404
        },
        "weight_kg": 14.5,
        "technologies": ["Dolby Atmos", "DTS:X Pro", "IMAX Enhanced", "Auro 3D", "Audyssey MultEQ XT32", "Dirac Live"]
      }
    },
    {
      "name": "CINEMA 40",
      "series": "CINEMA",
      "category": "AV receivari",
      "subcategory": "Nema",
      "description": "Premium 9.2-kanalni AV receiver za kućno kino.",
      "longDescription": "Marantz CINEMA 40 je 9.2-kanalni AV receiver s 11.2-kanalnom obradom, podrškom za 8K i Audyssey MultEQ XT32, idealan za vrhunske kućne kino sustave i streaming.",
      "intended_use": ["Kućno kino", "Streaming"],
      "price_usd": 2500,
      "finishes": ["Crna", "Srebrno-zlatna"],
      "imageUrl": "https://raw.githubusercontent.com/MikiMix-Git/SonusArtBA/refs/heads/main/logos/Marantz.png",
      "warranty_duration": 2,
      "release_year": 2022,
      "comparison_score": 87,
      "specifications": {
        "type": "AV receiver",
        "min_frequency": 20,
        "max_frequency": 20000,
        "amplifier_power": "125W po kanalu (8Ω, 2 kanala)",
        "amplifier_power_watts": 125,
        "inputs": ["7x HDMI 2.1 (8K)", "2x optički", "2x koaksijalni", "4x analogni RCA", "Phono MM"],
        "outputs": ["2x HDMI (1x eARC)", "2x subwoofer", "11.2 pre-out"],
        "connectivity": ["HEOS", "Bluetooth", "AirPlay 2", "Wi-Fi", "Spotify Connect"],
        "dimensions": {
          "height_mm": 165,
          "width_mm": 440,
          "depth_mm": 404
        },
        "weight_kg": 13.5,
        "technologies": ["Dolby Atmos", "DTS:X", "IMAX Enhanced", "Audyssey MultEQ XT32"]
      }
    },
    {
      "name": "CINEMA 50",
      "series": "CINEMA",
      "category": "AV receivari",
      "subcategory": "Nema",
      "description": "Snažan 9.2-kanalni AV receiver za kućno kino.",
      "longDescription": "Marantz CINEMA 50 je 9.2-kanalni AV receiver s podrškom za 8K, Dolby Atmos i HEOS, pružajući uravnotežen zvuk za kućne kino sustave i multi-room streaming.",
      "intended_use": ["Kućno kino", "Streaming"],
      "price_usd": 2000,
      "finishes": ["Crna", "Srebrno-zlatna"],
      "imageUrl": "https://raw.githubusercontent.com/MikiMix-Git/SonusArtBA/refs/heads/main/logos/Marantz.png",
      "warranty_duration": 2,
      "release_year": 2022,
      "comparison_score": 86,
      "specifications": {
        "type": "AV receiver",
        "min_frequency": 20,
        "max_frequency": 20000,
        "amplifier_power": "110W po kanalu (8Ω, 2 kanala)",
        "amplifier_power_watts": 110,
        "inputs": ["6x HDMI 2.1 (8K)", "2x optički", "2x koaksijalni", "4x analogni RCA", "Phono MM"],
        "outputs": ["2x HDMI (1x eARC)", "2x subwoofer", "11.2 pre-out"],
        "connectivity": ["HEOS", "Bluetooth", "AirPlay 2", "Wi-Fi", "Spotify Connect"],
        "dimensions": {
          "height_mm": 165,
          "width_mm": 440,
          "depth_mm": 404
        },
        "weight_kg": 13.5,
        "technologies": ["Dolby Atmos", "DTS:X", "IMAX Enhanced", "Audyssey MultEQ XT32"]
      }
    },
    {
      "name": "CINEMA 60",
      "series": "CINEMA",
      "category": "AV receivari",
      "subcategory": "Nema",
      "description": "7.2-kanalni AV receiver za kompaktne kino sustave.",
      "longDescription": "Marantz CINEMA 60 je 7.2-kanalni AV receiver s podrškom za 8K, Dolby Atmos i HEOS, idealan za manje kućne kino sustave i streaming.",
      "intended_use": ["Kućno kino", "Streaming"],
      "price_usd": 1700,
      "finishes": ["Crna", "Srebrno-zlatna"],
      "imageUrl": "https://raw.githubusercontent.com/MikiMix-Git/SonusArtBA/refs/heads/main/logos/Marantz.png",
      "warranty_duration": 2,
      "release_year": 2022,
      "comparison_score": 85,
      "specifications": {
        "type": "AV receiver",
        "min_frequency": 20,
        "max_frequency": 20000,
        "amplifier_power": "100W po kanalu (8Ω, 2 kanala)",
        "amplifier_power_watts": 100,
        "inputs": ["6x HDMI 2.1 (3x 8K, 3x 4K)", "2x optički", "2x koaksijalni", "4x analogni RCA", "Phono MM"],
        "outputs": ["2x HDMI (1x eARC)", "2x subwoofer", "7.2 pre-out"],
        "connectivity": ["HEOS", "Bluetooth", "AirPlay 2", "Wi-Fi", "Spotify Connect"],
        "dimensions": {
          "height_mm": 165,
          "width_mm": 440,
          "depth_mm": 404
        },
        "weight_kg": 11.0,
        "technologies": ["Dolby Atmos", "DTS:X", "Audyssey MultEQ XT"]
      }
    },
    {
      "name": "CINEMA 70s",
      "series": "CINEMA",
      "category": "AV receivari",
      "subcategory": "Nema",
      "description": "Kompaktni 7.2-kanalni AV receiver za male prostore.",
      "longDescription": "Marantz CINEMA 70s je tanak 7.2-kanalni AV receiver s podrškom za 8K i Dolby Atmos, idealan za kompaktne kućne kino sustave i streaming.",
      "intended_use": ["Kućno kino", "Streaming"],
      "price_usd": 1000,
      "finishes": ["Crna", "Srebrno-zlatna"],
      "imageUrl": "https://raw.githubusercontent.com/MikiMix-Git/SonusArtBA/refs/heads/main/logos/Marantz.png",
      "warranty_duration": 2,
      "release_year": 2022,
      "comparison_score": 84,
      "specifications": {
        "type": "AV receiver",
        "min_frequency": 20,
        "max_frequency": 20000,
        "amplifier_power": "50W po kanalu (8Ω, 2 kanala)",
        "amplifier_power_watts": 50,
        "inputs": ["6x HDMI 2.1 (3x 8K, 3x 4K)", "1x optički", "1x koaksijalni", "2x analogni RCA"],
        "outputs": ["1x HDMI (eARC)", "2x subwoofer", "7.2 pre-out"],
        "connectivity": ["HEOS", "Bluetooth", "AirPlay 2", "Wi-Fi", "Spotify Connect"],
        "dimensions": {
          "height_mm": 104,
          "width_mm": 440,
          "depth_mm": 368
        },
        "weight_kg": 8.7,
        "technologies": ["Dolby Atmos", "DTS:X", "Audyssey MultEQ"]
      }
    },
    {
      "name": "NR1510",
      "series": "NR",
      "category": "AV receivari",
      "subcategory": "Nema",
      "description": "Tanki 5.2-kanalni AV receiver za proračunske sustave.",
      "longDescription": "Marantz NR1510 je tanak 5.2-kanalni AV receiver s podrškom za 4K i HEOS, idealan za manje kućne kino sustave po pristupačnoj cijeni.",
      "intended_use": ["Kućno kino", "Streaming"],
      "price_usd": 599,
      "finishes": ["Crna", "Srebrno-zlatna"],
      "imageUrl": "https://raw.githubusercontent.com/MikiMix-Git/SonusArtBA/refs/heads/main/logos/Marantz.png",
      "warranty_duration": 2,
      "release_year": 2020,
      "comparison_score": 83,
      "specifications": {
        "type": "AV receiver",
        "min_frequency": 20,
        "max_frequency": 20000,
        "amplifier_power": "50W po kanalu (8Ω, 2 kanala)",
        "amplifier_power_watts": 50,
        "inputs": ["5x HDMI (4K)", "1x optički", "1x koaksijalni", "3x analogni RCA", "Phono MM"],
        "outputs": ["1x HDMI (ARC)", "2x subwoofer", "5.2 pre-out"],
        "connectivity": ["HEOS", "Bluetooth", "AirPlay 2", "Wi-Fi"],
        "dimensions": {
          "height_mm": 104,
          "width_mm": 440,
          "depth_mm": 378
        },
        "weight_kg": 8.2,
        "technologies": ["DTS HD Master", "Audyssey MultEQ"]
      }
    },
    {
      "name": "NR1711",
      "series": "NR",
      "category": "AV receivari",
      "subcategory": "Nema",
      "description": "Tanki 7.2-kanalni AV receiver za kompaktne sustave.",
      "longDescription": "Marantz NR1711 je tanak 7.2-kanalni AV receiver s podrškom za 8K i Dolby Atmos, idealan za kompaktne kućne kino sustave i streaming.",
      "intended_use": ["Kućno kino", "Streaming"],
      "price_usd": 999,
      "finishes": ["Crna", "Srebrno-zlatna"],
      "imageUrl": "https://raw.githubusercontent.com/MikiMix-Git/SonusArtBA/refs/heads/main/logos/Marantz.png",
      "warranty_duration": 2,
      "release_year": 2020,
      "comparison_score": 84,
      "specifications": {
        "type": "AV receiver",
        "min_frequency": 20,
        "max_frequency": 20000,
        "amplifier_power": "50W po kanalu (8Ω, 2 kanala)",
        "amplifier_power_watts": 50,
        "inputs": ["6x HDMI (1x 8K, 5x 4K)", "1x optički", "1x koaksijalni", "3x analogni RCA", "Phono MM"],
        "outputs": ["1x HDMI (eARC)", "2x subwoofer", "7.2 pre-out"],
        "connectivity": ["HEOS", "Bluetooth", "AirPlay 2", "Wi-Fi"],
        "dimensions": {
          "height_mm": 104,
          "width_mm": 440,
          "depth_mm": 378
        },
        "weight_kg": 8.4,
        "technologies": ["Dolby Atmos", "DTS:X", "Audyssey MultEQ"]
      }
    },
    {
      "name": "SR7015",
      "series": "SR",
      "category": "AV receivari",
      "subcategory": "Nema",
      "description": "Snažan 9.2-kanalni AV receiver za kućno kino.",
      "longDescription": "Marantz SR7015 je 9.2-kanalni AV receiver s podrškom za 8K, Dolby Atmos, DTS:X i IMAX Enhanced, pružajući vrhunski zvuk za kućne kino sustave.",
      "intended_use": ["Kućno kino", "Streaming"],
      "price_usd": 2300,
      "finishes": ["Crna", "Srebrno-zlatna"],
      "imageUrl": "https://raw.githubusercontent.com/MikiMix-Git/SonusArtBA/refs/heads/main/logos/Marantz.png",
      "warranty_duration": 2,
      "release_year": 2020,
      "comparison_score": 87,
      "specifications": {
        "type": "AV receiver",
        "min_frequency": 20,
        "max_frequency": 20000,
        "amplifier_power": "125W po kanalu (8Ω, 2 kanala)",
        "amplifier_power_watts": 125,
        "inputs": ["7x HDMI (1x 8K)", "2x optički", "2x koaksijalni", "4x analogni RCA", "Phono MM"],
        "outputs": ["2x HDMI (1x eARC)", "2x subwoofer", "11.2 pre-out"],
        "connectivity": ["HEOS", "Bluetooth", "AirPlay 2", "Wi-Fi", "Spotify Connect"],
        "dimensions": {
          "height_mm": 185,
          "width_mm": 440,
          "depth_mm": 411
        },
        "weight_kg": 14.2,
        "technologies": ["Dolby Atmos", "DTS:X", "IMAX Enhanced", "Audyssey MultEQ XT32"]
      }
    },
    {
      "name": "SR8015",
      "series": "SR",
      "category": "AV receivari",
      "subcategory": "Nema",
      "description": "Premium 11.2-kanalni AV receiver za kućno kino.",
      "longDescription": "Marantz SR8015 je 11.2-kanalni AV receiver s 13.2-kanalnom obradom, podrškom za 8K i snažnim pojačanjem, idealan za vrhunske kućne kino sustave.",
      "intended_use": ["Kućno kino", "Streaming"],
      "price_usd": 3200,
      "finishes": ["Crna", "Srebrno-zlatna"],
      "imageUrl": "https://raw.githubusercontent.com/MikiMix-Git/SonusArtBA/refs/heads/main/logos/Marantz.png",
      "warranty_duration": 2,
      "release_year": 2020,
      "comparison_score": 88,
      "specifications": {
        "type": "AV receiver",
        "min_frequency": 20,
        "max_frequency": 20000,
        "amplifier_power": "140W po kanalu (8Ω, 2 kanala)",
        "amplifier_power_watts": 140,
        "inputs": ["7x HDMI (1x 8K)", "2x optički", "2x koaksijalni", "5x analogni RCA", "Phono MM"],
        "outputs": ["2x HDMI (1x eARC)", "2x subwoofer", "13.2 pre-out"],
        "connectivity": ["HEOS", "Bluetooth", "AirPlay 2", "Wi-Fi", "Spotify Connect"],
        "dimensions": {
          "height_mm": 185,
          "width_mm": 440,
          "depth_mm": 460
        },
        "weight_kg": 17.6,
        "technologies": ["Dolby Atmos", "DTS:X", "IMAX Enhanced", "Audyssey MultEQ XT32"]
      }
    },
    {
      "name": "Model 10",
      "series": "10 Series",
      "category": "Pojačala",
      "subcategory": "Integrirana pojačala",
      "description": "Referentno integrirano pojačalo za audiofile.",
      "longDescription": "Marantz Model 10 je najmoćnije integrirano pojačalo s Purifi Class D tehnologijom, pružajući 250W po kanalu i izuzetno nisku distorziju za Hi-Fi sustave.",
      "intended_use": ["Hi-Fi stereo"],
      "price_usd": 15000,
      "finishes": ["Crna", "Srebrno-zlatna"],
      "imageUrl": "https://raw.githubusercontent.com/MikiMix-Git/SonusArtBA/refs/heads/main/logos/Marantz.png",
      "warranty_duration": 2,
      "release_year": 2024,
      "comparison_score": 90,
      "specifications": {
        "type": "Integrirano pojačalo",
        "min_frequency": 20,
        "max_frequency": 20000,
        "amplifier_power": "250W po kanalu (8Ω)",
        "amplifier_power_watts": 250,
        "inputs": ["2x XLR", "3x RCA", "Phono MM/MC"],
        "outputs": ["XLR pre-out", "RCA pre-out", "Slušalice"],
        "connectivity": [],
        "dimensions": {
          "height_mm": 129,
          "width_mm": 440,
          "depth_mm": 414
        },
        "weight_kg": 18.4,
        "technologies": ["Purifi Class D", "HDAM", "Balanced Audio"]
      }
    },
    {
      "name": "Model 50",
      "series": "Nema",
      "category": "Pojačala",
      "subcategory": "Integrirana pojačala",
      "description": "Integrirano pojačalo za Hi-Fi sustave.",
      "longDescription": "Marantz Model 50 je integrirano pojačalo s HDAM tehnologijom, pružajući čist i topao zvuk za Hi-Fi sustave po pristupačnoj cijeni.",
      "intended_use": ["Hi-Fi stereo"],
      "price_usd": 1800,
      "finishes": ["Crna", "Srebrno-zlatna"],
      "imageUrl": "https://raw.githubusercontent.com/MikiMix-Git/SonusArtBA/refs/heads/main/logos/Marantz.png",
      "warranty_duration": 2,
      "release_year": 2023,
      "comparison_score": 86,
      "specifications": {
        "type": "Integrirano pojačalo",
        "min_frequency": 20,
        "max_frequency": 20000,
        "amplifier_power": "70W po kanalu (8Ω)",
        "amplifier_power_watts": 70,
        "inputs": ["4x RCA", "Phono MM"],
        "outputs": ["RCA pre-out", "Slušalice"],
        "connectivity": [],
        "dimensions": {
          "height_mm": 130,
          "width_mm": 440,
          "depth_mm": 384
        },
        "weight_kg": 14.2,
        "technologies": ["HDAM", "Current Feedback"]
      }
    },
    {
      "name": "AMP 10",
      "series": "10 Series",
      "category": "Pojačala",
      "subcategory": "Snaga pojačala",
      "description": "Referentno pojačalo snage za kućno kino.",
      "longDescription": "Marantz AMP 10 je 16-kanalno pojačalo snage s 200W po kanalu, idealno za vrhunske kućne kino sustave s Dolby Atmos i DTS:X.",
      "intended_use": ["Kućno kino"],
      "price_usd": 7000,
      "finishes": ["Crna", "Srebrno-zlatna"],
      "imageUrl": "https://raw.githubusercontent.com/MikiMix-Git/SonusArtBA/refs/heads/main/logos/Marantz.png",
      "warranty_duration": 2,
      "release_year": 2023,
      "comparison_score": 89,
      "specifications": {
        "type": "Pojačalo snage",
        "min_frequency": 20,
        "max_frequency": 20000,
        "amplifier_power": "200W po kanalu (8Ω)",
        "amplifier_power_watts": 200,
        "inputs": ["16x RCA", "16x XLR"],
        "outputs": [],
        "connectivity": [],
        "dimensions": {
          "height_mm": 191,
          "width_mm": 440,
          "depth_mm": 464
        },
        "weight_kg": 19.8,
        "technologies": ["HDAM", "Class D"]
      }
    },
    {
      "name": "PM8006",
      "series": "Nema",
      "category": "Pojačala",
      "subcategory": "Integrirana pojačala",
      "description": "Integrirano pojačalo za audiofile.",
      "longDescription": "Marantz PM8006 je integrirano pojačalo s HDAM tehnologijom i phono ulazom, pružajući topao i detaljan zvuk za Hi-Fi sustave.",
      "intended_use": ["Hi-Fi stereo"],
      "price_usd": 1200,
      "finishes": ["Crna", "Srebrno-zlatna"],
      "imageUrl": "https://raw.githubusercontent.com/MikiMix-Git/SonusArtBA/refs/heads/main/logos/Marantz.png",
      "warranty_duration": 2,
      "release_year": 2020,
      "comparison_score": 85,
      "specifications": {
        "type": "Integrirano pojačalo",
        "min_frequency": 20,
        "max_frequency": 20000,
        "amplifier_power": "70W po kanalu (8Ω)",
        "amplifier_power_watts": 70,
        "inputs": ["5x RCA", "Phono MM"],
        "outputs": ["RCA pre-out", "Slušalice"],
        "connectivity": [],
        "dimensions": {
          "height_mm": 128,
          "width_mm": 440,
          "depth_mm": 379
        },
        "weight_kg": 12.1,
        "technologies": ["HDAM", "Current Feedback"]
      }
    },
    {
      "name": "CD 50n",
      "series": "Nema",
      "category": "CD plejeri",
      "subcategory": "Nema",
      "description": "Mrežni CD plejer za Hi-Fi sustave.",
      "longDescription": "Marantz CD 50n je mrežni CD plejer s HEOS i HDMI ARC, idealan za reprodukciju CD-ova i streaming visoke kvalitete.",
      "intended_use": ["Hi-Fi stereo", "Streaming"],
      "price_usd": 1800,
      "finishes": ["Crna", "Srebrno-zlatna"],
      "imageUrl": "https://raw.githubusercontent.com/MikiMix-Git/SonusArtBA/refs/heads/main/logos/Marantz.png",
      "warranty_duration": 2,
      "release_year": 2023,
      "comparison_score": 86,
      "specifications": {
        "type": "CD plejer",
        "min_frequency": 20,
        "max_frequency": 20000,
        "inputs": ["1x HDMI ARC", "1x optički", "1x koaksijalni", "1x USB-A"],
        "outputs": ["1x RCA", "1x koaksijalni", "1x optički"],
        "connectivity": ["HEOS", "Bluetooth", "AirPlay 2", "Wi-Fi", "Spotify Connect"],
        "dimensions": {
          "height_mm": 130,
          "width_mm": 440,
          "depth_mm": 424
        },
        "weight_kg": 8.5,
        "technologies": ["HEOS", "HDAM", "ESS Sabre DAC"]
      }
    },
    {
      "name": "SACD 30n",
      "series": "Nema",
      "category": "SACD plejeri",
      "subcategory": "Nema",
      "description": "SACD i mrežni plejer za audiofile.",
      "longDescription": "Marantz SACD 30n je SACD i mrežni plejer s HEOS i HDAM tehnologijom, pružajući vrhunski zvuk za CD, SACD i streaming.",
      "intended_use": ["Hi-Fi stereo", "Streaming"],
      "price_usd": 3000,
      "finishes": ["Crna", "Srebrno-zlatna"],
      "imageUrl": "https://raw.githubusercontent.com/MikiMix-Git/SonusArtBA/refs/heads/main/logos/Marantz.png",
      "warranty_duration": 2,
      "release_year": 2020,
      "comparison_score": 87,
      "specifications": {
        "type": "SACD plejer",
        "min_frequency": 20,
        "max_frequency": 20000,
        "inputs": ["1x USB-A", "1x optički", "1x koaksijalni"],
        "outputs": ["1x RCA", "1x XLR", "1x koaksijalni", "1x optički"],
        "connectivity": ["HEOS", "Bluetooth", "AirPlay 2", "Wi-Fi"],
        "dimensions": {
          "height_mm": 130,
          "width_mm": 440,
          "depth_mm": 424
        },
        "weight_kg": 13.5,
        "technologies": ["HEOS", "HDAM", "ESS Sabre DAC"]
      }
    },
    {
      "name": "ND8006",
      "series": "Nema",
      "category": "Mrežni plejeri",
      "subcategory": "Nema",
      "description": "Mrežni plejer i CD plejer za streaming.",
      "longDescription": "Marantz ND8006 je mrežni plejer i CD plejer s HEOS i ESS Sabre DAC-om, idealan za streaming i reprodukciju CD-ova visoke kvalitete.",
      "intended_use": ["Hi-Fi stereo", "Streaming"],
      "price_usd": 1500,
      "finishes": ["Crna", "Srebrno-zlatna"],
      "imageUrl": "https://raw.githubusercontent.com/MikiMix-Git/SonusArtBA/refs/heads/main/logos/Marantz.png",
      "warranty_duration": 2,
      "release_year": 2020,
      "comparison_score": 85,
      "specifications": {
        "type": "Mrežni plejer",
        "min_frequency": 20,
        "max_frequency": 20000,
        "inputs": ["1x USB-A", "2x optički", "1x koaksijalni"],
        "outputs": ["1x RCA", "1x koaksijalni", "1x optički"],
        "connectivity": ["HEOS", "Bluetooth", "AirPlay 2", "Wi-Fi"],
        "dimensions": {
          "height_mm": 106,
          "width_mm": 440,
          "depth_mm": 369
        },
        "weight_kg": 8.0,
        "technologies": ["HEOS", "ESS Sabre DAC"]
      }
    },
    {
      "name": "Melody X",
      "series": "Melody",
      "category": "Integrirani sustavi",
      "subcategory": "Nema",
      "description": "Kompaktni all-in-one Hi-Fi sustav.",
      "longDescription": "Marantz Melody X (M-CR612) je all-in-one sustav s CD plejerom, DAB/FM tunerom i HEOS streamingom, idealan za kompaktne Hi-Fi sustave.",
      "intended_use": ["Hi-Fi stereo", "Streaming"],
      "price_usd": 700,
      "finishes": ["Crna", "Srebrno-zlatna"],
      "imageUrl": "https://raw.githubusercontent.com/MikiMix-Git/SonusArtBA/refs/heads/main/logos/Marantz.png",
      "warranty_duration": 2,
      "release_year": 2020,
      "comparison_score": 84,
      "specifications": {
        "type": "Integrirani sustav",
        "min_frequency": 20,
        "max_frequency": 20000,
        "amplifier_power": "60W po kanalu (6Ω)",
        "amplifier_power_watts": 60,
        "inputs": ["2x optički", "1x RCA", "1x USB-A"],
        "outputs": ["1x subwoofer", "1x slušalice"],
        "connectivity": ["HEOS", "Bluetooth", "AirPlay 2", "Wi-Fi", "DAB/FM"],
        "dimensions": {
          "height_mm": 111,
          "width_mm": 280,
          "depth_mm": 303
        },
        "weight_kg": 3.4,
        "technologies": ["HEOS", "DAB/FM", "Audyssey MultEQ"]
      }
    },
    {
      "name": "Horizon",
      "series": "Nema",
      "category": "Zvučnici",
      "subcategory": "Bežični zvučnici",
      "description": "Premium bežični zvučnik za Hi-Fi zvuk.",
      "longDescription": "Marantz Horizon je bežični zvučnik s vrhunskim dizajnom i HDAM tehnologijom, pružajući bogat zvuk za Hi-Fi i streaming aplikacije.",
      "intended_use": ["Hi-Fi stereo", "Streaming"],
      "price_usd": 3500,
      "finishes": ["Crna", "Bijela"],
      "imageUrl": "https://raw.githubusercontent.com/MikiMix-Git/SonusArtBA/refs/heads/main/logos/Marantz.png",
      "warranty_duration": 2,
      "release_year": 2023,
      "comparison_score": 87,
      "specifications": {
        "type": "Bežični zvučnik",
        "min_frequency": 30,
        "max_frequency": 20000,
        "amplifier_power": "100W (Class D)",
        "amplifier_power_watts": 100,
        "inputs": ["1x USB-C", "1x RCA"],
        "outputs": [],
        "connectivity": ["HEOS", "Bluetooth", "AirPlay 2", "Wi-Fi"],
        "dimensions": {
          "height_mm": 250,
          "width_mm": 300,
          "depth_mm": 300
        },
        "weight_kg": 6.5,
        "technologies": ["HDAM", "HEOS"]
      }
    },
    {
      "name": "Grand Horizon",
      "series": "Nema",
      "category": "Zvučnici",
      "subcategory": "Bežični zvučnici",
      "description": "Luksuzni bežični zvučnik za audiofile.",
      "longDescription": "Marantz Grand Horizon je premium bežični zvučnik s HDAM tehnologijom i snažnim pojačanjem, idealan za vrhunski Hi-Fi zvuk i streaming.",
      "intended_use": ["Hi-Fi stereo", "Streaming"],
      "price_usd": 5000,
      "finishes": ["Crna", "Bijela"],
      "imageUrl": "https://raw.githubusercontent.com/MikiMix-Git/SonusArtBA/refs/heads/main/logos/Marantz.png",
      "warranty_duration": 2,
      "release_year": 2023,
      "comparison_score": 88,
      "specifications": {
        "type": "Bežični zvučnik",
        "min_frequency": 25,
        "max_frequency": 20000,
        "amplifier_power": "150W (Class D)",
        "amplifier_power_watts": 150,
        "inputs": ["1x USB-C", "1x RCA"],
        "outputs": [],
        "connectivity": ["HEOS", "Bluetooth", "AirPlay 2", "Wi-Fi"],
        "dimensions": {
          "height_mm": 350,
          "width_mm": 400,
          "depth_mm": 400
        },
        "weight_kg": 10.0,
        "technologies": ["HDAM", "HEOS"]
      }
    }
  ]
}
